{
  "graphs": {
    "sort": {
      "adjacencyList": [
        [
          {
            "feature": "Decreasing",
            "method": "sort",
            "uuid": "74346850-1956-49d3-b20e-cfe8b65d95dc"
          },
          []
        ],
        [
          {
            "feature": "Increasing",
            "method": "sort",
            "uuid": "e7a40e04-2efe-4d76-8155-1641ac3108ee"
          },
          []
        ]
      ],
      "varMethodCalls": {},
      "featureMap": {
        "Increasing": [
          "sort"
        ],
        "Decreasing": [
          "sort"
        ]
      },
      "idMap": {
        "Increasing": "e7a40e04-2efe-4d76-8155-1641ac3108ee",
        "Decreasing": "74346850-1956-49d3-b20e-cfe8b65d95dc"
      }
    },
    "push": {
      "adjacencyList": [
        [
          {
            "feature": "Sorted",
            "method": "push",
            "uuid": "40e24c0c-33b7-45f4-8a00-670561826398"
          },
          [
            {
              "feature": "Limited",
              "method": "push",
              "uuid": "b73a3f02-e855-4441-94a6-b73ee3d31f94"
            },
            {
              "feature": "Base",
              "method": "push",
              "uuid": "3c9b1969-9b4c-4cbd-8b3b-f39d444b2092"
            }
          ]
        ],
        [
          {
            "feature": "Limited",
            "method": "push",
            "uuid": "b73a3f02-e855-4441-94a6-b73ee3d31f94"
          },
          [
            {
              "feature": "Base",
              "method": "push",
              "uuid": "3c9b1969-9b4c-4cbd-8b3b-f39d444b2092"
            }
          ]
        ],
        [
          {
            "feature": "Base",
            "method": "push",
            "uuid": "3c9b1969-9b4c-4cbd-8b3b-f39d444b2092"
          },
          []
        ]
      ],
      "varMethodCalls": [
        [
          {
            "feature": "Sorted",
            "method": "push",
            "uuid": "40e24c0c-33b7-45f4-8a00-670561826398"
          },
          [
            "sort"
          ]
        ]
      ],
      "featureMap": {
        "Limited": [
          "push"
        ],
        "Sorted": [
          "push"
        ],
        "Base": [
          "push"
        ]
      },
      "idMap": {
        "Limited": "b73a3f02-e855-4441-94a6-b73ee3d31f94",
        "Sorted": "40e24c0c-33b7-45f4-8a00-670561826398",
        "Base": "3c9b1969-9b4c-4cbd-8b3b-f39d444b2092"
      }
    }
  }
}
